tidynamics/VERSION
tidynamics/__init__.py
tidynamics/_correlation.py
tidynamics/core.py
tidynamics-1.1.2.dist-info/LICENSE
tidynamics-1.1.2.dist-info/METADATA
tidynamics-1.1.2.dist-info/WHEEL
tidynamics-1.1.2.dist-info/top_level.txt
tidynamics-1.1.2.dist-info/RECORD
