Metadata-Version: 2.1
Name: tidynamics
Version: 1.1.2
Summary: Tiny package to compute dynamics correlations
Author-email: Pierre de Buyl <pdebuyl@pdebuyl.be>
License: BSD-3-Clause
Classifier: License :: OSI Approved :: BSD License
Classifier: Programming Language :: Python :: 3
Requires-Python: >=3.7
Provides-Extra: test
License-File: LICENSE
